polynomial_generator/polynomial.py
polynomial_generator/polynomial_app.py
polynomial_generator/polynomial_cli.py
polynomial_generator/pyinstaller_script.py
polynomial_generator-0.1.1.dist-info/LICENSE
polynomial_generator-0.1.1.dist-info/METADATA
polynomial_generator-0.1.1.dist-info/WHEEL
polynomial_generator-0.1.1.dist-info/entry_points.txt
polynomial_generator-0.1.1.dist-info/RECORD
