Metadata-Version: 2.1
Name: polynomial-generator
Version: 0.1.1
Summary: A Python package for generating polynomial expressions
License: MIT
Author: Hermann Agossou
Author-email: agossouhermann7@gmail.com
Requires-Python: >=3.8,<3.13
Classifier: License :: OSI Approved :: MIT License
Classifier: Programming Language :: Python :: 3
Classifier: Programming Language :: Python :: 3.8
Classifier: Programming Language :: Python :: 3.9
Classifier: Programming Language :: Python :: 3.10
Classifier: Programming Language :: Python :: 3.11
Classifier: Programming Language :: Python :: 3.12
